glovpy/__init__.py
glovpy/install.py
glovpy/train.py
glovpy/utils.py
glovpy-0.2.0.dist-info/LICENSE
glovpy-0.2.0.dist-info/METADATA
glovpy-0.2.0.dist-info/WHEEL
glovpy-0.2.0.dist-info/RECORD
